dotserializer/__init__.py
dotserializer/dotserializer.py
dotserializer-0.0.2.dist-info/METADATA
dotserializer-0.0.2.dist-info/WHEEL
dotserializer-0.0.2.dist-info/top_level.txt
dotserializer-0.0.2.dist-info/RECORD
