Metadata-Version: 2.1
Name: dotserializer
Version: 0.0.2
Summary: Transmit and receive Serial data and divide the stream into packets with NLSM protocol.
Home-page: https://github.com/uncertainty-cc/NewLine-Serializaiton-Method
Author: Rath Robotics
Author-email: tk@uncertainty.email
Classifier: Programming Language :: Python :: 3
Classifier: License :: OSI Approved :: MIT License
Classifier: Operating System :: OS Independent
Requires-Python: >=3.6
Requires-Dist: pyserial
